tsic/__init__.py
tsic/tsic.py
tsic-2.0.2.dist-info/LICENSE
tsic-2.0.2.dist-info/METADATA
tsic-2.0.2.dist-info/WHEEL
tsic-2.0.2.dist-info/entry_points.txt
tsic-2.0.2.dist-info/top_level.txt
tsic-2.0.2.dist-info/RECORD
