Metadata-Version: 2.1
Name: tsic
Version: 2.0.2
Summary: Receive temperature readings from TSic 206/306/506/716 sensor chips on Raspberry Pi
Home-page: https://github.com/grillbaer/python-tsic
Author: Grillbaer
Author-email: holgflei+tsic@gmail.com
License: UNKNOWN
Keywords: raspberrypi,raspberry,tsic,gpio,temperature,sensor
Platform: UNKNOWN
Classifier: Programming Language :: Python :: 3
Classifier: License :: OSI Approved :: Apache Software License
Classifier: Operating System :: Other OS
Classifier: Topic :: Software Development :: Embedded Systems
Classifier: Topic :: Scientific/Engineering :: Physics
Requires-Dist: pigpio
